hamtaa_texttools-2.0.0.dist-info/licenses/LICENSE
texttools/__init__.py
texttools/models.py
texttools/py.typed
texttools/core/__init__.py
texttools/core/exceptions.py
texttools/core/internal_models.py
texttools/core/utils.py
texttools/core/operators/__init__.py
texttools/core/operators/async_operator.py
texttools/core/operators/sync_operator.py
texttools/prompts/augment.yaml
texttools/prompts/categorize.yaml
texttools/prompts/extract_entities.yaml
texttools/prompts/extract_keywords.yaml
texttools/prompts/is_fact.yaml
texttools/prompts/is_question.yaml
texttools/prompts/merge_questions.yaml
texttools/prompts/propositionize.yaml
texttools/prompts/run_custom.yaml
texttools/prompts/summarize.yaml
texttools/prompts/to_question.yaml
texttools/prompts/translate.yaml
texttools/tools/__init__.py
texttools/tools/async_tools.py
texttools/tools/sync_tools.py
hamtaa_texttools-2.0.0.dist-info/METADATA
hamtaa_texttools-2.0.0.dist-info/WHEEL
hamtaa_texttools-2.0.0.dist-info/top_level.txt
hamtaa_texttools-2.0.0.dist-info/RECORD
