Metadata-Version: 2.4
Name: hamtaa-texttools
Version: 2.0.0
Summary: A high-level NLP toolkit built on top of modern LLMs.
Author-email: Tohidi <the.mohammad.tohidi@gmail.com>, Erfan Moosavi <erfanmoosavi84@gmail.com>, Montazer <montazerh82@gmail.com>, Givechi <mohamad.m.givechi@gmail.com>, Zareshahi <a.zareshahi1377@gmail.com>
Maintainer-email: Erfan Moosavi <erfanmoosavi84@gmail.com>, Tohidi <the.mohammad.tohidi@gmail.com>
License: MIT
Keywords: nlp,llm,text-processing,openai
Classifier: Development Status :: 5 - Production/Stable
Classifier: License :: OSI Approved :: MIT License
Classifier: Topic :: Scientific/Engineering :: Artificial Intelligence
Classifier: Topic :: Text Processing
Classifier: Operating System :: OS Independent
Requires-Python: >=3.11
License-File: LICENSE
Requires-Dist: openai>=1.97.1
Requires-Dist: pydantic>=2.0.0
Requires-Dist: pyyaml>=6.0
Dynamic: license-file
